fastapi_auth_middlewares/__init__.py
fastapi_auth_middlewares/auth_middleware.py
fastapi_auth_middlewares-0.1.0.dist-info/LICENSE
fastapi_auth_middlewares-0.1.0.dist-info/METADATA
fastapi_auth_middlewares-0.1.0.dist-info/WHEEL
fastapi_auth_middlewares-0.1.0.dist-info/top_level.txt
fastapi_auth_middlewares-0.1.0.dist-info/RECORD
