Metadata-Version: 2.1
Name: fastapi_auth_middlewares
Version: 0.1.0
Summary: A middleware for securing fastapi application.
Author-email: Laxman Maharjan <lxmnmrzn17@gmail.com>
Project-URL: Homepage, https://github.com/LaxmanMaharjan/fastapi-auth-middleware
Project-URL: Issues, https://github.com/LaxmanMaharjan/fastapi-auth-middleware/issues
Project-URL: Repository, https://github.com/LaxmanMaharjan/fastapi-auth-middleware
Classifier: Programming Language :: Python :: 3
Classifier: License :: OSI Approved :: MIT License
Classifier: Operating System :: OS Independent
Classifier: Topic :: Internet
Classifier: Topic :: Security
Classifier: Topic :: Software Development :: Libraries :: Python Modules
Classifier: Topic :: Software Development :: Libraries
Classifier: Topic :: Software Development
Requires-Python: >=3.8
License-File: LICENSE
Requires-Dist: fastapi >=0.75.0
Requires-Dist: PyJWT >=2.8.0
